RangeSlider/RangeSlider.py
RangeSlider/__init__.py
RangeSlider-2023.7.2.dist-info/METADATA
RangeSlider-2023.7.2.dist-info/WHEEL
RangeSlider-2023.7.2.dist-info/top_level.txt
RangeSlider-2023.7.2.dist-info/RECORD
