Metadata-Version: 2.1
Name: RangeSlider
Version: 2023.7.2
Summary: Python tkinter widget for range selection in slider widget structure with two handles
Home-page: https://github.com/harshvinay752/RangeSlider
Author: Harsh Agarwal
Author-email: harshvinay752@gmail.com
License: MIT
Download-URL: https://github.com/harshvinay752/RangeSlider/archive/refs/tags/2023.07.2.tar.gz
Keywords: Python,tkinter,range,slider,two handle,selector,widget
Platform: UNKNOWN
Classifier: Development Status :: 3 - Alpha
Classifier: Intended Audience :: Developers
Classifier: Topic :: Software Development :: Build Tools
Classifier: License :: OSI Approved :: MIT License
Classifier: Programming Language :: Python :: 3
Classifier: Programming Language :: Python :: 3.4
Classifier: Programming Language :: Python :: 3.5
Classifier: Programming Language :: Python :: 3.6
Classifier: Programming Language :: Python :: 3.7
Classifier: Programming Language :: Python :: 3.8
Classifier: Programming Language :: Python :: 3.9
Classifier: Programming Language :: Python :: 3.10
